LICENSE
README.md
setup.py
pypi_scraper/__init__.py
udemy_scraper.egg-info/PKG-INFO
udemy_scraper.egg-info/SOURCES.txt
udemy_scraper.egg-info/dependency_links.txt
udemy_scraper.egg-info/requires.txt
udemy_scraper.egg-info/top_level.txt